pr2md/__init__.py
pr2md/__main__.py
pr2md/cli.py
pr2md/exceptions.py
pr2md/formatter.py
pr2md/issue_extractor.py
pr2md/models.py
pr2md/pr_extractor.py
pr2md/py.typed
pr2md/reference_downloader.py
pr2md/reference_parser.py
pr2md-1.0.10.dist-info/licenses/LICENSE.md
pr2md-1.0.10.dist-info/METADATA
pr2md-1.0.10.dist-info/WHEEL
pr2md-1.0.10.dist-info/entry_points.txt
pr2md-1.0.10.dist-info/top_level.txt
pr2md-1.0.10.dist-info/RECORD
