Metadata-Version: 2.4
Name: PR2MD
Version: 1.0.10
Summary: Pull Request Markdown Generator
Author: tboy1337
License: MIT
Project-URL: Homepage, https://github.com/tboy1337/PR2MD
Project-URL: Repository, https://github.com/tboy1337/PR2MD
Classifier: Development Status :: 4 - Beta
Classifier: Intended Audience :: Developers
Classifier: License :: OSI Approved :: MIT License
Classifier: Operating System :: OS Independent
Classifier: Programming Language :: Python :: 3
Classifier: Programming Language :: Python :: 3.13
Classifier: Topic :: Software Development :: Version Control :: Git
Classifier: Typing :: Typed
Requires-Python: >=3.13
License-File: LICENSE.md
Dynamic: license-file
